wildguard/__init__.py
wildguard/utils.py
wildguard/wildguard.py
wildguard-1.0.1.dist-info/LICENSE.md
wildguard-1.0.1.dist-info/METADATA
wildguard-1.0.1.dist-info/WHEEL
wildguard-1.0.1.dist-info/top_level.txt
wildguard-1.0.1.dist-info/RECORD
