Metadata-Version: 2.1
Name: wildguard
Version: 1.0.1
Summary: WildGuard safety classification inference
Author-email: Kavel Rao <kavelrao@cs.washington.edu>, Seungju Han <wade3han@snu.ac.kr>
Project-URL: Homepage, https://github.com/allenai/wildguard
Project-URL: Issues, https://github.com/allenai/wildguard/issues
Classifier: Programming Language :: Python :: 3
Classifier: Operating System :: OS Independent
Requires-Python: >=3.10
License-File: LICENSE.md
Requires-Dist: torch >=2.3.0
Requires-Dist: tqdm >=4.66.2
Requires-Dist: transformers >=4.40.2
Requires-Dist: vllm >=0.4.2
